causal_test_again/CODEOWNERS
causal_test_again/__init__.py
causal_test_again/src/__init__.py
causal_test_again/src/models/__init__.py
causal_test_again/src/models/analyser_model/__init__.py
causal_test_again/src/models/analyser_model/ab_analyser.py
causal_test_again/src/models/analyser_model/analyser.py
causal_test_again/src/models/analyser_model/diff_in_diff_analyser.py
causal_test_again/src/models/analyser_model/fitters/__init__.py
causal_test_again/src/models/analyser_model/fitters/basic_fitter.py
causal_test_again/src/models/analyser_model/fitters/bootstrap_fitter.py
causal_test_again/src/models/analyser_model/fitters/fitter.py
causal_test_again/src/models/configuration_model/__init__.py
causal_test_again/src/models/configuration_model/base_objects.py
causal_test_again/src/models/configuration_model/config.py
causal_test_again/src/models/data_model.py
causal_test_again/src/models/message/__init__.py
causal_test_again/src/models/message/enums.py
causal_test_again/src/models/message/message.py
causal_test_again/src/models/preprocessor_model/__init__.py
causal_test_again/src/models/preprocessor_model/ab/__init__.py
causal_test_again/src/models/preprocessor_model/ab/distribution_preprocessor.py
causal_test_again/src/models/preprocessor_model/ab/flicker_preprocessor.py
causal_test_again/src/models/preprocessor_model/ab/imbalance_preprocessor.py
causal_test_again/src/models/preprocessor_model/ab/log_transform_preprocessor.py
causal_test_again/src/models/preprocessor_model/base.py
causal_test_again/src/models/preprocessor_model/diff_in_diff/__init__.py
causal_test_again/src/models/preprocessor_model/diff_in_diff/matching_preprocessor.py
causal_test_again/src/models/preprocessor_model/diff_in_diff/prep_did_preprocessor.py
causal_test_again/src/models/result_model/__init__.py
causal_test_again/src/models/result_model/result.py
causal_test_again/src/pipeline/__init__.py
causal_test_again/src/pipeline/experiment_pipelines/__init__.py
causal_test_again-0.1.67.dist-info/LICENSE.txt
causal_test_again-0.1.67.dist-info/METADATA
causal_test_again-0.1.67.dist-info/WHEEL
causal_test_again-0.1.67.dist-info/RECORD
