Metadata-Version: 2.1
Name: causal-test-again
Version: 0.1.67
Summary: A Scalable Causal Inference Library
Author: DoorDash
Requires-Python: >=3.7.1,<=3.11.4
Classifier: Programming Language :: Python :: 3
Classifier: Programming Language :: Python :: 3.8
Classifier: Programming Language :: Python :: 3.9
Classifier: Programming Language :: Python :: 3.10
Classifier: Programming Language :: Python :: 3.11
Requires-Dist: joblib
Requires-Dist: matplotlib (==3.5.3)
Requires-Dist: numpy (==1.21.6)
Requires-Dist: pandas (==1.3.5)
Requires-Dist: pydantic (==1.10.2)
Requires-Dist: scipy (==1.7.3)
Requires-Dist: setuptools (>=65.5.1,<66.0.0)
Requires-Dist: statsmodels (==0.13.5)
Project-URL: Bug Tracker, https://github.com/doordash/causal_platform/issues
